{
"meta":{"test_sets":[],"test_metrics":[],"learn_metrics":[{"best_value":"Min","name":"RMSE"}],"launch_mode":"Train","parameters":"","iteration_count":100,"learn_sets":["learn"],"name":"experiment"},
"iterations":[
{"learn":[14.005006],"iteration":0,"passed_time":0.0007316157203,"remaining_time":0.07242995631},
{"learn":[13.14441192],"iteration":1,"passed_time":0.00135113025,"remaining_time":0.06620538224},
{"learn":[12.34258257],"iteration":2,"passed_time":0.001994709984,"remaining_time":0.06449562283},
{"learn":[11.64527793],"iteration":3,"passed_time":0.002482203828,"remaining_time":0.05957289187},
{"learn":[11.02766183],"iteration":4,"passed_time":0.003086645009,"remaining_time":0.05864625518},
{"learn":[10.43485794],"iteration":5,"passed_time":0.003709075857,"remaining_time":0.05810885509},
{"learn":[9.890641275],"iteration":6,"passed_time":0.004381946363,"remaining_time":0.0582172874},
{"learn":[9.492161212],"iteration":7,"passed_time":0.004957837012,"remaining_time":0.05701512564},
{"learn":[9.105082953],"iteration":8,"passed_time":0.005528019638,"remaining_time":0.05589442078},
{"learn":[8.674157135],"iteration":9,"passed_time":0.006048467133,"remaining_time":0.0544362042},
{"learn":[8.341743544],"iteration":10,"passed_time":0.006646896384,"remaining_time":0.05377943438},
{"learn":[8.049372916],"iteration":11,"passed_time":0.007212558716,"remaining_time":0.05289209725},
{"learn":[7.757318612],"iteration":12,"passed_time":0.007791592591,"remaining_time":0.05214373503},
{"learn":[7.522206899],"iteration":13,"passed_time":0.008388177568,"remaining_time":0.05152737649},
{"learn":[7.297756655],"iteration":14,"passed_time":0.008946056976,"remaining_time":0.05069432286},
{"learn":[7.088359431],"iteration":15,"passed_time":0.009489553057,"remaining_time":0.04982015355},
{"learn":[6.882113791],"iteration":16,"passed_time":0.01015218558,"remaining_time":0.0495665531},
{"learn":[6.704728832],"iteration":17,"passed_time":0.01072163838,"remaining_time":0.04884301927},
{"learn":[6.563881962],"iteration":18,"passed_time":0.01127864624,"remaining_time":0.04808264975},
{"learn":[6.418790279],"iteration":19,"passed_time":0.01179801499,"remaining_time":0.04719205997},
{"learn":[6.315756953],"iteration":20,"passed_time":0.01230716845,"remaining_time":0.0462983956},
{"learn":[6.210157751],"iteration":21,"passed_time":0.01282889109,"remaining_time":0.04548425023},
{"learn":[6.115058449],"iteration":22,"passed_time":0.01337380367,"remaining_time":0.04477316881},
{"learn":[6.014819884],"iteration":23,"passed_time":0.01387979605,"remaining_time":0.04395268749},
{"learn":[5.93117229],"iteration":24,"passed_time":0.01452836254,"remaining_time":0.04358508762},
{"learn":[5.844857622],"iteration":25,"passed_time":0.01507524066,"remaining_time":0.04290645418},
{"learn":[5.771145213],"iteration":26,"passed_time":0.01558521247,"remaining_time":0.04213779668},
{"learn":[5.704018229],"iteration":27,"passed_time":0.01609055239,"remaining_time":0.04137570616},
{"learn":[5.665806474],"iteration":28,"passed_time":0.01660067002,"remaining_time":0.04064301971},
{"learn":[5.616500369],"iteration":29,"passed_time":0.01713014918,"remaining_time":0.03997034808},
{"learn":[5.558023666],"iteration":30,"passed_time":0.01767236565,"remaining_time":0.03933526548},
{"learn":[5.510080976],"iteration":31,"passed_time":0.01818324286,"remaining_time":0.03863939108},
{"learn":[5.468747792],"iteration":32,"passed_time":0.01869472417,"remaining_time":0.03795595513},
{"learn":[5.429275534],"iteration":33,"passed_time":0.01929066302,"remaining_time":0.03744658115},
{"learn":[5.402117324],"iteration":34,"passed_time":0.01989355676,"remaining_time":0.03694517684},
{"learn":[5.367635151],"iteration":35,"passed_time":0.02044364953,"remaining_time":0.03634426582},
{"learn":[5.345181232],"iteration":36,"passed_time":0.02097846807,"remaining_time":0.03572009429},
{"learn":[5.319151269],"iteration":37,"passed_time":0.02150775975,"remaining_time":0.03509160801},
{"learn":[5.296134146],"iteration":38,"passed_time":0.02203427497,"remaining_time":0.03446386598},
{"learn":[5.269629003],"iteration":39,"passed_time":0.0225769222,"remaining_time":0.0338653833},
{"learn":[5.251147059],"iteration":40,"passed_time":0.02312034165,"remaining_time":0.03327073555},
{"learn":[5.248003302],"iteration":41,"passed_time":0.02333487406,"remaining_time":0.03222434989},
{"learn":[5.232376509],"iteration":42,"passed_time":0.02385440425,"remaining_time":0.03162095447},
{"learn":[5.213524255],"iteration":43,"passed_time":0.02438385142,"remaining_time":0.03103399271},
{"learn":[5.189691584],"iteration":44,"passed_time":0.02489820143,"remaining_time":0.03043113508},
{"learn":[5.166052198],"iteration":45,"passed_time":0.0254412742,"remaining_time":0.02986584362},
{"learn":[5.140406659],"iteration":46,"passed_time":0.02600577298,"remaining_time":0.02932565889},
{"learn":[5.118929684],"iteration":47,"passed_time":0.02651153845,"remaining_time":0.02872083332},
{"learn":[5.108792602],"iteration":48,"passed_time":0.02705786975,"remaining_time":0.0281622726},
{"learn":[5.098141225],"iteration":49,"passed_time":0.02756059318,"remaining_time":0.02756059318},
{"learn":[5.085926393],"iteration":50,"passed_time":0.02811833718,"remaining_time":0.02701565729},
{"learn":[5.067816804],"iteration":51,"passed_time":0.02876859804,"remaining_time":0.02655562896},
{"learn":[5.049834901],"iteration":52,"passed_time":0.02940638457,"remaining_time":0.0260773599},
{"learn":[5.03838627],"iteration":53,"passed_time":0.03003827746,"remaining_time":0.02558816228},
{"learn":[5.033534248],"iteration":54,"passed_time":0.03043882521,"remaining_time":0.02490449336},
{"learn":[5.023726885],"iteration":55,"passed_time":0.03098412465,"remaining_time":0.02434466937},
{"learn":[5.01290392],"iteration":56,"passed_time":0.03158433754,"remaining_time":0.02382678095},
{"learn":[5.005569127],"iteration":57,"passed_time":0.03215981939,"remaining_time":0.02328814507},
{"learn":[4.989969032],"iteration":58,"passed_time":0.03273992977,"remaining_time":0.02275147662},
{"learn":[4.976762446],"iteration":59,"passed_time":0.0333655641,"remaining_time":0.0222437094},
{"learn":[4.967222715],"iteration":60,"passed_time":0.03391525513,"remaining_time":0.02168352377},
{"learn":[4.954407599],"iteration":61,"passed_time":0.03447173441,"remaining_time":0.02112783722},
{"learn":[4.942125056],"iteration":62,"passed_time":0.03506138755,"remaining_time":0.02059160856},
{"learn":[4.930230716],"iteration":63,"passed_time":0.03564607886,"remaining_time":0.02005091936},
{"learn":[4.921695642],"iteration":64,"passed_time":0.0362450605,"remaining_time":0.01951657104},
{"learn":[4.906405625],"iteration":65,"passed_time":0.03685817661,"remaining_time":0.01898754553},
{"learn":[4.894330248],"iteration":66,"passed_time":0.03751777229,"remaining_time":0.01847890277},
{"learn":[4.88211557],"iteration":67,"passed_time":0.03818138572,"remaining_time":0.01796771092},
{"learn":[4.877946398],"iteration":68,"passed_time":0.03873686548,"remaining_time":0.01740351928},
{"learn":[4.863182126],"iteration":69,"passed_time":0.03929175083,"remaining_time":0.01683932178},
{"learn":[4.84646533],"iteration":70,"passed_time":0.03981210607,"remaining_time":0.01626128276},
{"learn":[4.838014752],"iteration":71,"passed_time":0.04042307996,"remaining_time":0.01572008665},
{"learn":[4.82981137],"iteration":72,"passed_time":0.0410624939,"remaining_time":0.01518749774},
{"learn":[4.817094767],"iteration":73,"passed_time":0.04166881729,"remaining_time":0.01464039526},
{"learn":[4.808314151],"iteration":74,"passed_time":0.04217827577,"remaining_time":0.01405942526},
{"learn":[4.796235023],"iteration":75,"passed_time":0.04278572329,"remaining_time":0.01351128104},
{"learn":[4.784434534],"iteration":76,"passed_time":0.04337839691,"remaining_time":0.01295718349},
{"learn":[4.774402487],"iteration":77,"passed_time":0.04395020917,"remaining_time":0.01239621284},
{"learn":[4.76731896],"iteration":78,"passed_time":0.04452025975,"remaining_time":0.01183449943},
{"learn":[4.75934113],"iteration":79,"passed_time":0.04506593228,"remaining_time":0.01126648307},
{"learn":[4.754106378],"iteration":80,"passed_time":0.04564322529,"remaining_time":0.01070643556},
{"learn":[4.744002932],"iteration":81,"passed_time":0.04624940919,"remaining_time":0.01015230934},
{"learn":[4.731700554],"iteration":82,"passed_time":0.04684706064,"remaining_time":0.009595181094},
{"learn":[4.723284153],"iteration":83,"passed_time":0.04740326837,"remaining_time":0.009029193975},
{"learn":[4.712232782],"iteration":84,"passed_time":0.04799659406,"remaining_time":0.008469987188},
{"learn":[4.703046867],"iteration":85,"passed_time":0.04855823679,"remaining_time":0.007904829244},
{"learn":[4.698601855],"iteration":86,"passed_time":0.04912548598,"remaining_time":0.007340589859},
{"learn":[4.692429407],"iteration":87,"passed_time":0.04967422995,"remaining_time":0.006773758629},
{"learn":[4.675027364],"iteration":88,"passed_time":0.05026030576,"remaining_time":0.006211947903},
{"learn":[4.662368584],"iteration":89,"passed_time":0.0509022912,"remaining_time":0.005655810133},
{"learn":[4.646206172],"iteration":90,"passed_time":0.05149405086,"remaining_time":0.005092818217},
{"learn":[4.641245848],"iteration":91,"passed_time":0.05202939464,"remaining_time":0.004524295186},
{"learn":[4.633900435],"iteration":92,"passed_time":0.05261236629,"remaining_time":0.003960070581},
{"learn":[4.624738236],"iteration":93,"passed_time":0.05319017412,"remaining_time":0.003395117497},
{"learn":[4.612798287],"iteration":94,"passed_time":0.0537292057,"remaining_time":0.002827852932},
{"learn":[4.605222001],"iteration":95,"passed_time":0.05423624185,"remaining_time":0.002259843411},
{"learn":[4.601725912],"iteration":96,"passed_time":0.05474337546,"remaining_time":0.001693094087},
{"learn":[4.59722371],"iteration":97,"passed_time":0.0553147328,"remaining_time":0.001128872098},
{"learn":[4.580235665],"iteration":98,"passed_time":0.05591844453,"remaining_time":0.000564832773},
{"learn":[4.57591791],"iteration":99,"passed_time":0.05650131872,"remaining_time":0}
]}